MANIFEST.in
Makefile
README
setup.py
test/__init__.py
test/test_serialize_yaml.py
tiddlywebplugins/__init__.py
tiddlywebplugins/simplerizer.py
tiddlywebplugins/yaml.py
tiddlywebplugins.yaml.egg-info/PKG-INFO
tiddlywebplugins.yaml.egg-info/SOURCES.txt
tiddlywebplugins.yaml.egg-info/dependency_links.txt
tiddlywebplugins.yaml.egg-info/namespace_packages.txt
tiddlywebplugins.yaml.egg-info/requires.txt
tiddlywebplugins.yaml.egg-info/top_level.txt