Metadata-Version: 1.0
Name: tiddlywebplugins.yaml
Version: 0.2
Summary: TiddlyWeb YAML Serializer
Home-page: http://pypi.python.org/pypi/tiddlywebplugins.yaml
Author: Paul Downey
Author-email: paul.downey@whatfettle.com
License: UNKNOWN
Platform: Posix; MacOS X; Windows
